headwaters/__init__.py
headwaters/cli.py
headwaters/server/__init__.py
headwaters/server/server.py
headwaters/source/__init__.py
headwaters/source/source.py
headwaters/source/schemas/__init__.py
headwaters/source/schemas/fruit_sales.json
headwaters/stream/__init__.py
headwaters/stream/stream.py
headwaters/ui/__init__.py
headwaters/ui/favicon.ico
headwaters/ui/index.html
headwaters/ui/assets/AboutView.213d76f4.js
headwaters/ui/assets/__init__.py
headwaters/ui/assets/index.51285248.js
headwaters/ui/assets/index.7f83872c.css
headwaters/ui-dev/package-lock.json
headwaters/ui-dev/package.json
headwaters-0.20.1.dist-info/LICENSE.md
headwaters-0.20.1.dist-info/METADATA
headwaters-0.20.1.dist-info/WHEEL
headwaters-0.20.1.dist-info/entry_points.txt
headwaters-0.20.1.dist-info/top_level.txt
headwaters-0.20.1.dist-info/RECORD
