Metadata-Version: 2.1
Name: headwaters
Version: 0.20.1
Summary: Simplified stream sources for event-driven application development.
Home-page: https://github.com/headwaters-ai/headwaters
Author: Ben Dyer (FifthHour)
Author-email: ben@fifthhour.co.uk
License: UNKNOWN
Project-URL: Bug Tracker, https://github.com/headwaters-ai/headwaters/issues
Platform: UNKNOWN
Classifier: Programming Language :: Python :: 3
Classifier: License :: OSI Approved :: MIT License
Classifier: Operating System :: OS Independent
Requires-Python: >=3.8
License-File: LICENSE.md
Requires-Dist: flask-socketio
Requires-Dist: simple-websocket
Requires-Dist: pandas
Requires-Dist: marshmallow
Requires-Dist: colorama
Requires-Dist: flask-cors
